dcache/__init__.py
dcache/backends.py
dcache/dcache.py
dcache/exceptions.py
dcache/keys.py
dcache/serializers.py
dcache-0.0.2.dist-info/LICENSE
dcache-0.0.2.dist-info/METADATA
dcache-0.0.2.dist-info/WHEEL
dcache-0.0.2.dist-info/top_level.txt
dcache-0.0.2.dist-info/RECORD
