Metadata-Version: 2.1
Name: dcache
Version: 0.0.2
Summary: Distributed Cache for Humans
Home-page: https://github.com/HBN3tw0rk/dcache
Author: HBN3tw0rk
License: GNU Lesser General Public License v2.1
Keywords: dcache
Classifier: Development Status :: 2 - Pre-Alpha
Classifier: Intended Audience :: Developers
Classifier: License :: OSI Approved :: GNU Lesser General Public License v2 (LGPLv2)
Classifier: Natural Language :: English
Classifier: Programming Language :: Python :: 3
Classifier: Programming Language :: Python :: 3.6
Classifier: Programming Language :: Python :: 3.7
Classifier: Programming Language :: Python :: 3.8
Requires-Python: >=3.6
License-File: LICENSE
